{
  "tasks": [
    {
      "name": "Определить требования к проекту",
      "description": "Собрать и проанализировать требования заказчика для определения функциональных и нефункциональных требований к системе.",
      "assigned_to": "Frontender1"
    },
    {
      "name": "Разработать структуру базы данных",
      "description": "Создать ER-диаграмму и определить таблицы, поля и связи для хранения данных в базе.",
      "assigned_to": "Backender"
    },
    {
      "name": "Реализовать API для фронтенда",
      "description": "Разработать RESTful API для взаимодействия фронтенда с бэкендом и базой данных.",
      "assigned_to": "Frontender1"
    },
    {
      "name": "Разработать интерфейс пользователя",
      "description": "Создать интерактивный пользовательский интерфейс с использованием HTML, CSS и JavaScript.",
      "assigned_to": "Frontender2"
    },
    {
      "name": "Интеграция фронтенда с бэкендом",
      "description": "Подключить фронтенд к RESTful API, написанному на FAST API.",
      "assigned_to": "Frontender1"
    },
    {
      "name": "Обучение модели машинного обучения",
      "description": "Загрузить данные и обучить модель машинного обучения для анализа и предложения задач.",
      "assigned_to": "ML"
    },
    {
      "name": "Тестирование модели машинного обучения",
      "description": "Провести тестирование модели машинного обучения для оценки ее точности и производительности.",
      "assigned_to": "ML"
    },
    {
      "name": "Интеграция модели машинного обучения в приложение",
      "description": "Интегрировать обученную модель машинного обучения в приложение для анализа и предложения задач.",
      "assigned_to": "ML"
    },
    {
      "name": "Документирование API и архитектуры системы",
      "description": "Документировать RESTful API и архитектуру системы для последующего использования и поддержки.",
      "assigned_to": "Frontender1"
    },
    {
      "name": "Оптимизация производительности приложения",
      "description": "Оптимизировать производительность приложения путем минимизации запросов к базе данных и улучшения структуры кода.",
      "assigned_to": "Frontender1"
    },
    {
      "name": "Тестирование приложения",
      "description": "Провести модульное и интеграционное тестирование приложения для выявления и устранения багов.",
      "assigned_to": "Frontender1"
    },
    {
      "name": "Деплой приложения на сервер",
      "description": "Выполнить деплой готового приложения на сервер для публичного доступа.",
      "assigned_to": "Frontender1"
    },
    {
      "name": "Мониторинг и поддержка приложения",
      "description": "Установить мониторинг и настроить логирование для отслеживания состояния и производительности приложения.",
      "assigned_to": "Backender"
    }
  ]
}
